kentro-0.2.3.dist-info/METADATA
kentro-0.2.3.dist-info/WHEEL
kentro/__init__.py
kentro/kentro.cp312-win_amd64.pyd
kentro-0.2.3.dist-info/RECORD
