Metadata-Version: 2.4
Name: kentro
Version: 0.2.3
Classifier: Development Status :: 4 - Beta
Classifier: Intended Audience :: Developers
Classifier: Intended Audience :: Science/Research
Classifier: License :: OSI Approved :: MIT License
Classifier: License :: OSI Approved :: Apache Software License
Classifier: Operating System :: OS Independent
Classifier: Programming Language :: Python :: 3
Classifier: Programming Language :: Python :: 3.8
Classifier: Programming Language :: Python :: 3.9
Classifier: Programming Language :: Python :: 3.10
Classifier: Programming Language :: Python :: 3.11
Classifier: Programming Language :: Python :: 3.12
Classifier: Programming Language :: Rust
Classifier: Topic :: Scientific/Engineering :: Artificial Intelligence
Classifier: Topic :: Software Development :: Libraries :: Python Modules
Requires-Dist: numpy>=1.20.0
Summary: High-performance K-Means clustering library with Python bindings
Keywords: clustering,kmeans,machine-learning,unsupervised-learning
Home-Page: https://github.com/pisa-engine/kentro
Author-email: Your Name <your.email@example.com>
License: MIT OR Apache-2.0
Requires-Python: >=3.8
Project-URL: Homepage, https://github.com/yourusername/kentro
Project-URL: Repository, https://github.com/yourusername/kentro
Project-URL: Documentation, https://github.com/yourusername/kentro#readme
Project-URL: Issues, https://github.com/yourusername/kentro/issues
